[
  {"id": "AGR-COMP-001", "regime": "USDA", "category": "organic_certification", "title": "USDA Organic Certification", "description": "Maintain USDA organic certification per NOP standards for labeled organic products.", "severity": "Critical", "enforcement": "DocOnly", "citation": "7 CFR Part 205"},
  {"id": "AGR-COMP-002", "regime": "USDA", "category": "gmo_disclosure", "title": "Bioengineered Food Disclosure", "description": "Disclose bioengineered ingredients per USDA National Bioengineered Food Disclosure Standard.", "severity": "High", "enforcement": "BuildGate", "citation": "7 CFR Part 66"},
  {"id": "AGR-COMP-003", "regime": "USDA-APHIS", "category": "plant_health", "title": "Plant Protection Act", "description": "Comply with plant health import/export requirements per Plant Protection Act.", "severity": "Critical", "enforcement": "DocOnly", "citation": "7 USC 7701"},
  {"id": "AGR-COMP-004", "regime": "USDA-AMS", "category": "grading", "title": "Agricultural Grading Standards", "description": "Apply USDA grading standards for inspected commodities per Agricultural Marketing Act.", "severity": "Medium", "enforcement": "DocOnly", "citation": "7 USC 1621"},
  {"id": "AGR-COMP-005", "regime": "FDA-FSMA", "category": "produce_safety", "title": "Produce Safety Rule", "description": "Comply with FSMA Produce Safety Rule for fruit and vegetable growing and harvesting.", "severity": "Critical", "enforcement": "DocOnly", "citation": "21 CFR 112"},
  {"id": "AGR-COMP-006", "regime": "FDA-FSMA", "category": "produce_safety", "title": "Agricultural Water Standards", "description": "Apply microbial water quality standards for agricultural water per FSMA Produce Rule.", "severity": "High", "enforcement": "DocOnly", "citation": "21 CFR 112.44"},
  {"id": "AGR-COMP-007", "regime": "EPA-FIFRA", "category": "pesticide", "title": "FIFRA Pesticide Registration", "description": "Use only registered pesticides per FIFRA with label-compliant application.", "severity": "Critical", "enforcement": "BuildGate", "citation": "7 USC 136"},
  {"id": "AGR-COMP-008", "regime": "EPA-FIFRA", "category": "pesticide", "title": "Worker Protection Standard", "description": "Implement WPS for agricultural workers handling pesticides per EPA.", "severity": "Critical", "enforcement": "DocOnly", "citation": "40 CFR 170"},
  {"id": "AGR-COMP-009", "regime": "EPA", "category": "water_quality", "title": "CWA Agricultural Exemptions", "description": "Apply Clean Water Act Section 402 exemptions to routine agricultural activities.", "severity": "High", "enforcement": "DocOnly", "citation": "33 USC 1342"},
  {"id": "AGR-COMP-010", "regime": "EPA", "category": "nutrient_management", "title": "CAFO Nutrient Management", "description": "Maintain Nutrient Management Plan for Concentrated Animal Feeding Operations.", "severity": "High", "enforcement": "DocOnly", "citation": "40 CFR 122.23"},
  {"id": "AGR-COMP-011", "regime": "EPA-FRA", "category": "animal_waste", "title": "Livestock Manure Management", "description": "Apply EPA livestock waste management standards for CAFO discharge.", "severity": "Critical", "enforcement": "DocOnly", "citation": "40 CFR 412"},
  {"id": "AGR-COMP-012", "regime": "OSHA", "category": "farm_safety", "title": "OSHA Agricultural Operations", "description": "Apply OSHA agricultural operations standards where employer has 11+ employees.", "severity": "High", "enforcement": "DocOnly", "citation": "29 CFR 1928"},
  {"id": "AGR-COMP-013", "regime": "OSHA", "category": "farm_safety", "title": "Grain Handling Safety", "description": "Apply OSHA grain handling facilities standard for elevators and mills.", "severity": "Critical", "enforcement": "DocOnly", "citation": "29 CFR 1910.272"},
  {"id": "AGR-COMP-014", "regime": "FDA", "category": "animal_feed", "title": "FDA CVM Animal Feed Rules", "description": "Comply with FDA Center for Veterinary Medicine animal feed safety requirements.", "severity": "Critical", "enforcement": "DocOnly", "citation": "21 CFR 500"},
  {"id": "AGR-COMP-015", "regime": "USDA-FSIS", "category": "meat_poultry", "title": "FSIS Inspection Services", "description": "Submit to USDA FSIS inspection for federally regulated meat and poultry.", "severity": "Critical", "enforcement": "DocOnly", "citation": "9 CFR 300"},
  {"id": "AGR-COMP-016", "regime": "USDA-FSIS", "category": "haccp", "title": "HACCP for Meat and Poultry", "description": "Implement HACCP plans for federally regulated meat, poultry, and egg products.", "severity": "Critical", "enforcement": "DocOnly", "citation": "9 CFR 417"},
  {"id": "AGR-COMP-017", "regime": "FDA-FSMA", "category": "preventive_controls", "title": "FSMA Preventive Controls for Human Food", "description": "Implement Preventive Controls per FSMA for covered food facilities.", "severity": "Critical", "enforcement": "DocOnly", "citation": "21 CFR 117"},
  {"id": "AGR-COMP-018", "regime": "FDA-FSMA", "category": "preventive_controls", "title": "FSMA Preventive Controls for Animal Food", "description": "Implement Preventive Controls per FSMA for covered animal food facilities.", "severity": "Critical", "enforcement": "DocOnly", "citation": "21 CFR 507"},
  {"id": "AGR-COMP-019", "regime": "FDA-FSMA", "category": "food_defense", "title": "FSMA Intentional Adulteration Rule", "description": "Implement food defense plan for intentional adulteration per FSMA IA rule.", "severity": "Critical", "enforcement": "DocOnly", "citation": "21 CFR 121"},
  {"id": "AGR-COMP-020", "regime": "FDA-FSMA", "category": "sanitary_transportation", "title": "Sanitary Transportation Rule", "description": "Maintain sanitary transportation per FSMA for human and animal food.", "severity": "High", "enforcement": "DocOnly", "citation": "21 CFR 1 Subpart O"},
  {"id": "AGR-COMP-021", "regime": "FDA-FSMA", "category": "foreign_supplier", "title": "FSMA FSVP", "description": "Verify foreign suppliers per FSMA Foreign Supplier Verification Program.", "severity": "Critical", "enforcement": "DocOnly", "citation": "21 CFR 1 Subpart L"},
  {"id": "AGR-COMP-022", "regime": "FDA-FSMA", "category": "traceability", "title": "FSMA Traceability Rule", "description": "Maintain traceability records for high-risk foods per FSMA Section 204.", "severity": "High", "enforcement": "DocOnly", "citation": "21 CFR 1 Subpart S"},
  {"id": "AGR-COMP-023", "regime": "USDA-NRCS", "category": "conservation", "title": "Conservation Compliance", "description": "Meet USDA NRCS conservation compliance for farm program eligibility.", "severity": "Medium", "enforcement": "DocOnly", "citation": "7 CFR Part 12"},
  {"id": "AGR-COMP-024", "regime": "USDA-FSA", "category": "crop_insurance", "title": "Federal Crop Insurance", "description": "Apply USDA Federal Crop Insurance per Risk Management Agency rules.", "severity": "Medium", "enforcement": "DocOnly", "citation": "7 CFR 457"},
  {"id": "AGR-COMP-025", "regime": "USDA-AMS", "category": "country_of_origin", "title": "Country of Origin Labeling", "description": "Apply USDA AMS COOL requirements for muscle cuts and ground meats.", "severity": "Medium", "enforcement": "BuildGate", "citation": "7 CFR 65"},
  {"id": "AGR-COMP-026", "regime": "USDA-AMS", "category": "organic", "title": "NOP Organic Record Retention", "description": "Maintain organic operation records for 5 years per NOP.", "severity": "High", "enforcement": "DocOnly", "citation": "7 CFR 205.103"},
  {"id": "AGR-COMP-027", "regime": "DOL-FLSA", "category": "farm_labor", "title": "Farm Labor FLSA Rules", "description": "Apply FLSA agricultural exemptions and minimum wage rules correctly.", "severity": "Critical", "enforcement": "DocOnly", "citation": "29 USC 213(a)"},
  {"id": "AGR-COMP-028", "regime": "DOL-MSPA", "category": "migrant_workers", "title": "MSPA Worker Protections", "description": "Comply with Migrant and Seasonal Agricultural Worker Protection Act.", "severity": "Critical", "enforcement": "DocOnly", "citation": "29 USC 1801"},
  {"id": "AGR-COMP-029", "regime": "DOL-H2A", "category": "temporary_workers", "title": "H-2A Agricultural Worker Program", "description": "Comply with H-2A program requirements for temporary agricultural workers.", "severity": "High", "enforcement": "DocOnly", "citation": "20 CFR 655 Subpart B"},
  {"id": "AGR-COMP-030", "regime": "EPA-NEPA", "category": "environmental_review", "title": "NEPA Environmental Review", "description": "Apply NEPA environmental review for federal agricultural actions.", "severity": "Medium", "enforcement": "DocOnly", "citation": "42 USC 4321"},
  {"id": "AGR-COMP-031", "regime": "EPA-ESA", "category": "endangered_species", "title": "Endangered Species Act", "description": "Apply ESA protections to pesticide use affecting listed species.", "severity": "Critical", "enforcement": "DocOnly", "citation": "16 USC 1536"},
  {"id": "AGR-COMP-032", "regime": "EPA-CWA", "category": "wetlands", "title": "Swampbuster Wetland Conservation", "description": "Avoid farming wetlands without conservation plan per Swampbuster.", "severity": "High", "enforcement": "DocOnly", "citation": "16 USC 3821"},
  {"id": "AGR-COMP-033", "regime": "USDA-APHIS", "category": "animal_welfare", "title": "Animal Welfare Act", "description": "Comply with AWA for research, exhibition, and dealer activities with animals.", "severity": "Critical", "enforcement": "DocOnly", "citation": "7 USC 2131"},
  {"id": "AGR-COMP-034", "regime": "USDA-APHIS", "category": "animal_disease", "title": "Animal Disease Surveillance", "description": "Report reportable animal diseases to USDA APHIS per state requirements.", "severity": "Critical", "enforcement": "DocOnly", "citation": "9 CFR 71"},
  {"id": "AGR-COMP-035", "regime": "USDA-FSIS", "category": "humane_slaughter", "title": "Humane Methods of Slaughter Act", "description": "Apply humane handling and slaughter methods per HMSA.", "severity": "Critical", "enforcement": "DocOnly", "citation": "7 USC 1901"},
  {"id": "AGR-COMP-036", "regime": "FDA-Food-Defect", "category": "defect_levels", "title": "Food Defect Action Levels", "description": "Apply FDA food defect action levels for natural or unavoidable defects.", "severity": "Medium", "enforcement": "DocOnly", "citation": "FDA Food Defect Handbook"},
  {"id": "AGR-COMP-037", "regime": "GLOBALG.A.P.", "category": "voluntary_standards", "title": "GLOBALG.A.P. Certification", "description": "Maintain GLOBALG.A.P. Good Agricultural Practices for covered products.", "severity": "Medium", "enforcement": "DocOnly", "citation": "GlobalG.A.P. Standards"},
  {"id": "AGR-COMP-038", "regime": "SQF", "category": "food_safety_voluntary", "title": "SQF Certification", "description": "Maintain SQF food safety certification for covered commodities.", "severity": "Medium", "enforcement": "DocOnly", "citation": "SQF Code"},
  {"id": "AGR-COMP-039", "regime": "EPA-TSCA", "category": "chemical_control", "title": "TSCA Chemical Control", "description": "Comply with TSCA requirements for chemicals used in agricultural processing.", "severity": "High", "enforcement": "DocOnly", "citation": "15 USC 2601"},
  {"id": "AGR-COMP-040", "regime": "CDFA", "category": "state_agriculture", "title": "State-Specific Agricultural Rules", "description": "Comply with state Department of Agriculture rules for intrastate commerce.", "severity": "High", "enforcement": "DocOnly", "citation": "Various State Codes"},
  {"id": "AGR-COMP-041", "regime": "DEA", "category": "controlled_substances", "title": "Hemp Production", "description": "Comply with hemp production rules per USDA Domestic Hemp Production Program.", "severity": "High", "enforcement": "DocOnly", "citation": "7 CFR 990"},
  {"id": "AGR-COMP-042", "regime": "EPA", "category": "air_quality", "title": "Livestock Air Quality", "description": "Apply Clean Air Act requirements to CAFO air emissions where applicable.", "severity": "Medium", "enforcement": "DocOnly", "citation": "42 USC 7401"},
  {"id": "AGR-COMP-043", "regime": "FDA", "category": "dietary_supplements", "title": "Dietary Supplements GMP", "description": "Apply FDA cGMP for dietary supplement manufacturing.", "severity": "High", "enforcement": "DocOnly", "citation": "21 CFR 111"},
  {"id": "AGR-COMP-044", "regime": "USDA-RMA", "category": "crop_insurance", "title": "Good Farming Practices", "description": "Apply Good Farming Practices for federal crop insurance eligibility.", "severity": "Medium", "enforcement": "DocOnly", "citation": "7 CFR 457.8"},
  {"id": "AGR-COMP-045", "regime": "EPA-CERCLA", "category": "hazardous_release", "title": "CERCLA Hazardous Substance Reporting", "description": "Report releases of hazardous substances per CERCLA.", "severity": "Critical", "enforcement": "BuildGate", "citation": "42 USC 9601"},
  {"id": "AGR-COMP-046", "regime": "EPA-EPCRA", "category": "emergency_planning", "title": "EPCRA for Agricultural Facilities", "description": "Report EHS and TRI per EPCRA for agricultural processing facilities.", "severity": "High", "enforcement": "DocOnly", "citation": "42 USC 11001"},
  {"id": "AGR-COMP-047", "regime": "FDA", "category": "food_contact_substances", "title": "Food Contact Substances", "description": "Use only FDA-approved food contact substances in agricultural packaging.", "severity": "High", "enforcement": "BuildGate", "citation": "21 CFR 170.39"},
  {"id": "AGR-COMP-048", "regime": "FDA-cGMP", "category": "food_cgmp", "title": "Human Food cGMP", "description": "Apply FDA Current Good Manufacturing Practice for human food processing.", "severity": "Critical", "enforcement": "DocOnly", "citation": "21 CFR 117 Subpart B"},
  {"id": "AGR-COMP-049", "regime": "USDA-ERS", "category": "agricultural_data", "title": "NASS Agricultural Census", "description": "Respond to USDA NASS Census of Agriculture and surveys as required.", "severity": "Low", "enforcement": "DocOnly", "citation": "7 USC 2204g"},
  {"id": "AGR-COMP-050", "regime": "EU-CAP", "category": "common_agricultural_policy", "title": "EU Common Agricultural Policy", "description": "Comply with EU Common Agricultural Policy for EU-sold agricultural products.", "severity": "High", "enforcement": "DocOnly", "citation": "Regulation (EU) 2021/2115"},
  {"id": "AGR-COMP-051", "regime": "EU-Organic", "category": "organic_certification", "title": "EU Organic Regulation", "description": "Maintain EU organic certification for EU-sold organic products.", "severity": "Critical", "enforcement": "DocOnly", "citation": "Regulation (EU) 2018/848"},
  {"id": "AGR-COMP-052", "regime": "EU-Plant-Health", "category": "plant_health", "title": "EU Plant Health Regulation", "description": "Comply with EU Plant Health Regulation for plants and plant products.", "severity": "Critical", "enforcement": "DocOnly", "citation": "Regulation (EU) 2016/2031"},
  {"id": "AGR-COMP-053", "regime": "EU-Animal-Health", "category": "animal_health", "title": "EU Animal Health Law", "description": "Comply with EU Animal Health Law for livestock health and movement.", "severity": "Critical", "enforcement": "DocOnly", "citation": "Regulation (EU) 2016/429"},
  {"id": "AGR-COMP-054", "regime": "EU-GMO", "category": "gmo_labeling", "title": "EU GMO Labeling", "description": "Label GMO food products per EU Regulation 1829/2003 and 1830/2003.", "severity": "Critical", "enforcement": "BuildGate", "citation": "Regulation (EC) 1830/2003"},
  {"id": "AGR-COMP-055", "regime": "EU-Farm-to-Fork", "category": "sustainability", "title": "Farm to Fork Strategy", "description": "Align with EU Farm to Fork Strategy sustainability targets.", "severity": "Medium", "enforcement": "DocOnly", "citation": "EU Farm to Fork 2020"},
  {"id": "AGR-COMP-056", "regime": "GDPR", "category": "lawful_basis", "title": "Lawful Basis for Farm Worker Data", "description": "Document lawful basis for farm worker personal data processing.", "severity": "Critical", "enforcement": "BuildGate", "citation": "GDPR Article 6"},
  {"id": "AGR-COMP-057", "regime": "GDPR", "category": "breach_notification", "title": "72-Hour Breach Notification", "description": "Notify supervisory authority of personal data breach within 72 hours.", "severity": "Critical", "enforcement": "BuildGate", "citation": "GDPR Article 33"},
  {"id": "AGR-COMP-058", "regime": "GDPR", "category": "international_transfers", "title": "Cross-Border Transfer Safeguards", "description": "Use SCCs or adequacy decisions for personal data transfers outside EEA.", "severity": "High", "enforcement": "BuildGate", "citation": "GDPR Chapter V"},
  {"id": "AGR-COMP-059", "regime": "SOC2", "category": "trust_services", "title": "Security Trust Services Criteria", "description": "Implement controls aligned with AICPA TSC Common Criteria for security.", "severity": "High", "enforcement": "DocOnly", "citation": "AICPA TSC 100"},
  {"id": "AGR-COMP-060", "regime": "ISO-27001", "category": "isms", "title": "Agriculture ISMS", "description": "Establish ISMS for agricultural business systems including farm records.", "severity": "Medium", "enforcement": "DocOnly", "citation": "ISO/IEC 27001:2022"},
  {"id": "AGR-COMP-061", "regime": "ISO-14001", "category": "ems", "title": "Environmental Management System", "description": "Establish EMS per ISO 14001 for farm environmental impacts.", "severity": "Medium", "enforcement": "DocOnly", "citation": "ISO 14001:2015"},
  {"id": "AGR-COMP-062", "regime": "ISO-22000", "category": "food_safety_management", "title": "ISO 22000 Food Safety", "description": "Establish FSMS per ISO 22000 for food chain operations.", "severity": "Medium", "enforcement": "DocOnly", "citation": "ISO 22000:2018"},
  {"id": "AGR-COMP-063", "regime": "EPA-CAA", "category": "air_emissions", "title": "Agricultural Burning Rules", "description": "Comply with state and local agricultural burning regulations.", "severity": "Medium", "enforcement": "DocOnly", "citation": "Various State Codes"},
  {"id": "AGR-COMP-064", "regime": "USDA-APHIS", "category": "veterinary_biologics", "title": "Veterinary Biologics Act", "description": "Use only USDA-licensed veterinary biologics per VSTA.", "severity": "Critical", "enforcement": "BuildGate", "citation": "21 USC 151"},
  {"id": "AGR-COMP-065", "regime": "FDA-cGMP", "category": "dietary_supplements", "title": "Supplements cGMP", "description": "Apply FDA dietary supplement cGMP for manufacturing and labeling.", "severity": "High", "enforcement": "DocOnly", "citation": "21 CFR 111"},
  {"id": "AGR-COMP-066", "regime": "EPA-SDWA", "category": "drinking_water", "title": "Safe Drinking Water Act", "description": "Comply with SDWA for public water systems serving agricultural operations.", "severity": "Critical", "enforcement": "DocOnly", "citation": "42 USC 300f"},
  {"id": "AGR-COMP-067", "regime": "USDA-NRCS", "category": "wetland", "title": "Wetland Reserve Program", "description": "Apply Wetland Reserve Program rules for enrolled lands.", "severity": "Medium", "enforcement": "DocOnly", "citation": "7 CFR 1467"},
  {"id": "AGR-COMP-068", "regime": "Grower-Shipper-Agreement", "category": "contract_compliance", "title": "Grower-Shipper Agreements", "description": "Comply with grower-shipper contract terms and Perishable Agricultural Commodities Act.", "severity": "High", "enforcement": "DocOnly", "citation": "7 USC 499a"},
  {"id": "AGR-COMP-069", "regime": "USDA-AMS", "category": "check_off", "title": "Commodity Check-Off Programs", "description": "Remit check-off assessments per USDA AMS commodity promotion orders.", "severity": "Medium", "enforcement": "DocOnly", "citation": "7 USC 7411"},
  {"id": "AGR-COMP-070", "regime": "GlobalGAP-IFA", "category": "voluntary_standards", "title": "Integrated Farm Assurance", "description": "Apply GlobalG.A.P. Integrated Farm Assurance standards.", "severity": "Medium", "enforcement": "DocOnly", "citation": "GlobalG.A.P. IFA"},
  {"id": "AGR-COMP-071", "regime": "GMP", "category": "packaging", "title": "Good Manufacturing Practice Packaging", "description": "Apply GMP to food packaging manufacture and handling.", "severity": "High", "enforcement": "DocOnly", "citation": "21 CFR 110"},
  {"id": "AGR-COMP-072", "regime": "USDA-FGIS", "category": "grain_inspection", "title": "Federal Grain Inspection", "description": "Submit grain to USDA FGIS inspection for official weights and grades.", "severity": "Medium", "enforcement": "DocOnly", "citation": "7 USC 74"},
  {"id": "AGR-COMP-073", "regime": "Checkoff-Programs", "category": "marketing_orders", "title": "USDA Marketing Orders", "description": "Comply with federal marketing orders for covered commodities.", "severity": "Medium", "enforcement": "DocOnly", "citation": "7 USC 601"},
  {"id": "AGR-COMP-074", "regime": "FDA", "category": "labeling", "title": "FDA Food Labeling", "description": "Apply FDA food labeling requirements including nutrition facts panel.", "severity": "Critical", "enforcement": "BuildGate", "citation": "21 CFR 101"},
  {"id": "AGR-COMP-075", "regime": "USDA-APHIS", "category": "biotechnology", "title": "USDA BRS Biotechnology Rules", "description": "Comply with USDA APHIS BRS regulations for bioengineered plants.", "severity": "Critical", "enforcement": "DocOnly", "citation": "7 CFR Part 340"},
  {"id": "AGR-COMP-076", "regime": "FDA-Low-Acid", "category": "canning", "title": "Low-Acid Canned Food Regulations", "description": "Register low-acid canned food facilities and file process schedules with FDA.", "severity": "Critical", "enforcement": "DocOnly", "citation": "21 CFR 113"},
  {"id": "AGR-COMP-077", "regime": "FDA-Juice-HACCP", "category": "juice", "title": "Juice HACCP Rule", "description": "Apply HACCP to juice processing per FDA Juice HACCP rule.", "severity": "Critical", "enforcement": "DocOnly", "citation": "21 CFR 120"},
  {"id": "AGR-COMP-078", "regime": "FDA-Seafood-HACCP", "category": "seafood", "title": "Seafood HACCP Rule", "description": "Apply HACCP to seafood processing per FDA Seafood HACCP rule.", "severity": "Critical", "enforcement": "DocOnly", "citation": "21 CFR 123"},
  {"id": "AGR-COMP-079", "regime": "FDA-Egg", "category": "egg_safety", "title": "FDA Shell Egg Safety Rule", "description": "Apply Shell Egg Safety Rule for shell egg producers.", "severity": "Critical", "enforcement": "DocOnly", "citation": "21 CFR 118"},
  {"id": "AGR-COMP-080", "regime": "USDA-FSIS", "category": "food_labeling", "title": "FSIS Label Approval", "description": "Obtain FSIS label approval for covered meat and poultry products.", "severity": "High", "enforcement": "BuildGate", "citation": "9 CFR 412"},
  {"id": "AGR-COMP-081", "regime": "Codex-Alimentarius", "category": "international_standards", "title": "Codex Alimentarius Standards", "description": "Apply Codex Alimentarius food safety standards for international trade.", "severity": "Medium", "enforcement": "DocOnly", "citation": "FAO/WHO Codex"},
  {"id": "AGR-COMP-082", "regime": "EPA-WPS", "category": "worker_protection", "title": "Pesticide Worker Training", "description": "Train pesticide handlers and agricultural workers per WPS.", "severity": "High", "enforcement": "DocOnly", "citation": "40 CFR 170.501"},
  {"id": "AGR-COMP-083", "regime": "OSHA-Agriculture", "category": "field_sanitation", "title": "Field Sanitation Standard", "description": "Provide potable water, toilets, and handwashing per OSHA field sanitation standard.", "severity": "High", "enforcement": "DocOnly", "citation": "29 CFR 1928.110"},
  {"id": "AGR-COMP-084", "regime": "DOT", "category": "agricultural_vehicle", "title": "Agricultural Vehicle Exemptions", "description": "Apply agricultural vehicle exemptions to DOT hours of service and CDL requirements.", "severity": "Medium", "enforcement": "DocOnly", "citation": "49 CFR 395.1(k)"},
  {"id": "AGR-COMP-085", "regime": "USDA-OCIA", "category": "cooperatives", "title": "Agricultural Cooperative Filings", "description": "Apply USDA rules to agricultural cooperatives including Capper-Volstead protections.", "severity": "Medium", "enforcement": "DocOnly", "citation": "7 USC 291"},
  {"id": "AGR-COMP-086", "regime": "USDA-FSA", "category": "farm_subsidy", "title": "Farm Program Participation", "description": "Comply with Farm Service Agency program requirements including AGI limits.", "severity": "High", "enforcement": "DocOnly", "citation": "7 USC 1308"},
  {"id": "AGR-COMP-087", "regime": "USDA-Farm-Bill", "category": "farm_legislation", "title": "Farm Bill Compliance", "description": "Apply current Farm Bill commodity, conservation, and nutrition program rules.", "severity": "High", "enforcement": "DocOnly", "citation": "Agricultural Act"},
  {"id": "AGR-COMP-088", "regime": "NORTHERN-PLAINS-PROTECTIONS", "category": "sod_saver", "title": "Sodbuster Rules", "description": "Apply Sodbuster rules to limit cropland conversion of highly erodible land.", "severity": "Medium", "enforcement": "DocOnly", "citation": "16 USC 3811"},
  {"id": "AGR-COMP-089", "regime": "EPA-CWA", "category": "spill_prevention", "title": "SPCC for Oil Storage", "description": "Develop SPCC plan for farms storing 1,320+ gallons of oil.", "severity": "High", "enforcement": "DocOnly", "citation": "40 CFR 112"},
  {"id": "AGR-COMP-090", "regime": "OSHA-AG", "category": "grain_bin", "title": "Grain Bin Engulfment Prevention", "description": "Apply OSHA grain bin engulfment prevention standards.", "severity": "Critical", "enforcement": "DocOnly", "citation": "29 CFR 1910.272"},
  {"id": "AGR-COMP-091", "regime": "OSHA-AG", "category": "anhydrous_ammonia", "title": "Anhydrous Ammonia Handling", "description": "Apply OSHA anhydrous ammonia handling standards for fertilizer use.", "severity": "Critical", "enforcement": "DocOnly", "citation": "29 CFR 1910.111"},
  {"id": "AGR-COMP-092", "regime": "EPA", "category": "ag_waivers", "title": "Agricultural Stormwater Exemption", "description": "Apply agricultural stormwater exemption per CWA Section 402(l)(1).", "severity": "Low", "enforcement": "DocOnly", "citation": "33 USC 1342(l)"},
  {"id": "AGR-COMP-093", "regime": "USDA-Livestock-Mandatory-Reporting", "category": "market_reporting", "title": "Livestock Mandatory Price Reporting", "description": "Report livestock transactions per USDA AMS LMPR.", "severity": "High", "enforcement": "DocOnly", "citation": "7 USC 1636"},
  {"id": "AGR-COMP-094", "regime": "EU-AI-Act", "category": "ai_governance", "title": "EU AI Act for Agricultural AI", "description": "Classify precision agriculture AI per EU AI Act with transparency for generative systems.", "severity": "Medium", "enforcement": "DocOnly", "citation": "EU AI Act 2024"},
  {"id": "AGR-COMP-095", "regime": "BSA-OFAC", "category": "sanctions_screening", "title": "OFAC for Agricultural Exports", "description": "Screen export customers against OFAC sanctions list.", "severity": "Critical", "enforcement": "BuildGate", "citation": "31 CFR Chapter V"},
  {"id": "AGR-COMP-096", "regime": "USDA-MAP", "category": "market_access", "title": "Market Access Program", "description": "Apply MAP program rules for USDA export promotion cost-share.", "severity": "Low", "enforcement": "DocOnly", "citation": "7 USC 5623"},
  {"id": "AGR-COMP-097", "regime": "ICAC", "category": "international_cotton", "title": "International Cotton Advisory Committee", "description": "Comply with ICAC reporting for cotton-producing farms.", "severity": "Low", "enforcement": "DocOnly", "citation": "ICAC Rules"},
  {"id": "AGR-COMP-098", "regime": "USDA-MMPA", "category": "milk_marketing", "title": "Federal Milk Marketing Orders", "description": "Comply with Federal Milk Marketing Orders for Grade A milk.", "severity": "High", "enforcement": "DocOnly", "citation": "7 CFR 1000"},
  {"id": "AGR-COMP-099", "regime": "USDA-Organic-Livestock", "category": "organic_livestock", "title": "NOP Organic Livestock Rules", "description": "Apply NOP organic livestock rules including access to outdoors.", "severity": "High", "enforcement": "DocOnly", "citation": "7 CFR 205.238"},
  {"id": "AGR-COMP-100", "regime": "EU-Pesticide", "category": "pesticide_registration", "title": "EU Plant Protection Regulation", "description": "Comply with EU Regulation 1107/2009 for plant protection products.", "severity": "Critical", "enforcement": "DocOnly", "citation": "Regulation (EC) 1107/2009"}
]
